ipulse_shared_enums_ftredge/__init__.py
ipulse_shared_enums_ftredge/enums_common_utils.py
ipulse_shared_enums_ftredge/enums_data_eng.py
ipulse_shared_enums_ftredge/enums_logging.py
ipulse_shared_enums_ftredge/enums_module_fincore.py
ipulse_shared_enums_ftredge/enums_pulse.py
ipulse_shared_enums_ftredge/enums_solution_providers.py
ipulse_shared_enums_ftredge/pulse_enums.py
ipulse_shared_enums_ftredge-2.2.2.dist-info/LICENCE
ipulse_shared_enums_ftredge-2.2.2.dist-info/METADATA
ipulse_shared_enums_ftredge-2.2.2.dist-info/WHEEL
ipulse_shared_enums_ftredge-2.2.2.dist-info/top_level.txt
ipulse_shared_enums_ftredge-2.2.2.dist-info/RECORD
