Metadata-Version: 2.1
Name: ipulse_shared_enums_ftredge
Version: 2.2.2
Summary: Shared Enums for  Pulse Platform . Using AI for Asset Management and Financial Advisory.
Home-page: https://github.com/TheFutureEdge/ipulse_shared_enums
Author: Russlan Ramdowar
License-File: LICENCE
